odoo/addons/fieldservice_stock_request/README.rst
odoo/addons/fieldservice_stock_request/__init__.py
odoo/addons/fieldservice_stock_request/__manifest__.py
odoo/addons/fieldservice_stock_request/i18n/es.po
odoo/addons/fieldservice_stock_request/i18n/es_AR.po
odoo/addons/fieldservice_stock_request/i18n/fieldservice_stock_request.pot
odoo/addons/fieldservice_stock_request/i18n/it.po
odoo/addons/fieldservice_stock_request/i18n/pt_BR.po
odoo/addons/fieldservice_stock_request/models/__init__.py
odoo/addons/fieldservice_stock_request/models/fsm_order.py
odoo/addons/fieldservice_stock_request/models/stock_move_line.py
odoo/addons/fieldservice_stock_request/models/stock_request.py
odoo/addons/fieldservice_stock_request/models/stock_request_order.py
odoo/addons/fieldservice_stock_request/readme/CONFIGURE.md
odoo/addons/fieldservice_stock_request/readme/CONTRIBUTORS.md
odoo/addons/fieldservice_stock_request/readme/CREDITS.md
odoo/addons/fieldservice_stock_request/readme/DESCRIPTION.md
odoo/addons/fieldservice_stock_request/readme/ROADMAP.md
odoo/addons/fieldservice_stock_request/readme/USAGE.md
odoo/addons/fieldservice_stock_request/security/ir.model.access.csv
odoo/addons/fieldservice_stock_request/static/description/icon.png
odoo/addons/fieldservice_stock_request/static/description/index.html
odoo/addons/fieldservice_stock_request/tests/__init__.py
odoo/addons/fieldservice_stock_request/tests/test_fsm_stock_request.py
odoo/addons/fieldservice_stock_request/views/fsm_order.xml
odoo/addons/fieldservice_stock_request/views/stock.xml
odoo/addons/fieldservice_stock_request/views/stock_request.xml
odoo/addons/fieldservice_stock_request/views/stock_request_order.xml
odoo_addon_fieldservice_stock_request-17.0.1.2.0.2.dist-info/METADATA
odoo_addon_fieldservice_stock_request-17.0.1.2.0.2.dist-info/WHEEL
odoo_addon_fieldservice_stock_request-17.0.1.2.0.2.dist-info/top_level.txt
odoo_addon_fieldservice_stock_request-17.0.1.2.0.2.dist-info/RECORD
